<annotation>
    <folder>data</folder>
    <filename>220328_B097_3.jpg</filename>
    <source>
        <database>BSRL_HairFollicleDataset</database>
        <form>VOC</form>
        <image>HuaShanHospital</image>
    </source>
    <size>
        <width>1280</width>
        <height>1024</height>
        <depth>3</depth>
    </size>
    <segmented>0</segmented>
    <object>
        <class>premium</class>
        <pose>None</pose>
        <difficult>0</difficult>
        <bndbox>
            <xmin>681</xmin>
            <ymin>440</ymin>
            <xmax>713</xmax>
            <ymax>484</ymax>
        </bndbox>
    </object>
    <object>
        <class>premium</class>
        <pose>None</pose>
        <difficult>0</difficult>
        <bndbox>
            <xmin>664</xmin>
            <ymin>494</ymin>
            <xmax>705</xmax>
            <ymax>552</ymax>
        </bndbox>
    </object>
    <object>
        <class>premium</class>
        <pose>None</pose>
        <difficult>0</difficult>
        <bndbox>
            <xmin>796</xmin>
            <ymin>756</ymin>
            <xmax>812</xmax>
            <ymax>798</ymax>
        </bndbox>
    </object>
    <object>
        <class>premium</class>
        <pose>None</pose>
        <difficult>0</difficult>
        <bndbox>
            <xmin>732</xmin>
            <ymin>772</ymin>
            <xmax>756</xmax>
            <ymax>806</ymax>
        </bndbox>
    </object>
    <object>
        <class>premium</class>
        <pose>None</pose>
        <difficult>0</difficult>
        <bndbox>
            <xmin>704</xmin>
            <ymin>804</ymin>
            <xmax>724</xmax>
            <ymax>860</ymax>
        </bndbox>
    </object>
    <object>
        <class>premium</class>
        <pose>None</pose>
        <difficult>0</difficult>
        <bndbox>
            <xmin>171</xmin>
            <ymin>358</ymin>
            <xmax>212</xmax>
            <ymax>433</ymax>
        </bndbox>
    </object>
    <object>
        <class>premium</class>
        <pose>None</pose>
        <difficult>0</difficult>
        <bndbox>
            <xmin>129</xmin>
            <ymin>390</ymin>
            <xmax>182</xmax>
            <ymax>464</ymax>
        </bndbox>
    </object>
    <object>
        <class>premium</class>
        <pose>None</pose>
        <difficult>0</difficult>
        <bndbox>
            <xmin>1212</xmin>
            <ymin>347</ymin>
            <xmax>1246</xmax>
            <ymax>417</ymax>
        </bndbox>
    </object>
    <object>
        <class>premium</class>
        <pose>None</pose>
        <difficult>0</difficult>
        <bndbox>
            <xmin>1179</xmin>
            <ymin>366</ymin>
            <xmax>1243</xmax>
            <ymax>446</ymax>
        </bndbox>
    </object>
    <object>
        <class>undersize</class>
        <pose>None</pose>
        <difficult>0</difficult>
        <bndbox>
            <xmin>742</xmin>
            <ymin>392</ymin>
            <xmax>766</xmax>
            <ymax>472</ymax>
        </bndbox>
    </object>
    <object>
        <class>undersize</class>
        <pose>None</pose>
        <difficult>0</difficult>
        <bndbox>
            <xmin>248</xmin>
            <ymin>342</ymin>
            <xmax>268</xmax>
            <ymax>417</ymax>
        </bndbox>
    </object>
</annotation>
