<annotation>
    <folder>data</folder>
    <filename>230219_A153_4.jpg</filename>
    <source>
        <database>BSRL_HairFollicleDataset</database>
        <form>VOC</form>
        <image>HuaShanHospital</image>
    </source>
    <size>
        <width>1280</width>
        <height>1024</height>
        <depth>3</depth>
    </size>
    <segmented>0</segmented>
    <object>
        <class>premium</class>
        <pose>None</pose>
        <difficult>0</difficult>
        <bndbox>
            <xmin>368</xmin>
            <ymin>62</ymin>
            <xmax>500</xmax>
            <ymax>182</ymax>
        </bndbox>
    </object>
    <object>
        <class>premium</class>
        <pose>None</pose>
        <difficult>0</difficult>
        <bndbox>
            <xmin>318</xmin>
            <ymin>84</ymin>
            <xmax>451</xmax>
            <ymax>174</ymax>
        </bndbox>
    </object>
    <object>
        <class>premium</class>
        <pose>None</pose>
        <difficult>0</difficult>
        <bndbox>
            <xmin>561</xmin>
            <ymin>416</ymin>
            <xmax>696</xmax>
            <ymax>526</ymax>
        </bndbox>
    </object>
    <object>
        <class>premium</class>
        <pose>None</pose>
        <difficult>0</difficult>
        <bndbox>
            <xmin>552</xmin>
            <ymin>462</ymin>
            <xmax>779</xmax>
            <ymax>616</ymax>
        </bndbox>
    </object>
    <object>
        <class>premium</class>
        <pose>None</pose>
        <difficult>0</difficult>
        <bndbox>
            <xmin>936</xmin>
            <ymin>496</ymin>
            <xmax>1116</xmax>
            <ymax>617</ymax>
        </bndbox>
    </object>
    <object>
        <class>premium</class>
        <pose>None</pose>
        <difficult>0</difficult>
        <bndbox>
            <xmin>891</xmin>
            <ymin>523</ymin>
            <xmax>1064</xmax>
            <ymax>612</ymax>
        </bndbox>
    </object>
    <object>
        <class>single</class>
        <pose>None</pose>
        <difficult>0</difficult>
        <bndbox>
            <xmin>732</xmin>
            <ymin>33</ymin>
            <xmax>894</xmax>
            <ymax>139</ymax>
        </bndbox>
    </object>
    <object>
        <class>single</class>
        <pose>None</pose>
        <difficult>0</difficult>
        <bndbox>
            <xmin>136</xmin>
            <ymin>564</ymin>
            <xmax>276</xmax>
            <ymax>668</ymax>
        </bndbox>
    </object>
    <object>
        <class>single</class>
        <pose>None</pose>
        <difficult>0</difficult>
        <bndbox>
            <xmin>497</xmin>
            <ymin>702</ymin>
            <xmax>598</xmax>
            <ymax>784</ymax>
        </bndbox>
    </object>
    <object>
        <class>abnormal</class>
        <pose>None</pose>
        <difficult>0</difficult>
        <bndbox>
            <xmin>548</xmin>
            <ymin>790</ymin>
            <xmax>561</xmax>
            <ymax>776</ymax>
        </bndbox>
    </object>
    <object>
        <class>single</class>
        <pose>None</pose>
        <difficult>0</difficult>
        <bndbox>
            <xmin>1076</xmin>
            <ymin>854</ymin>
            <xmax>1278</xmax>
            <ymax>968</ymax>
        </bndbox>
    </object>
</annotation>
